sample_generated_20250730_01_package/__init__.py
sample_generated_20250730_01_package/cities.json
sample_generated_20250730_01_package/states_info.py
sample_generated_20250730_01_repo-0.0.0.dist-info/METADATA
sample_generated_20250730_01_repo-0.0.0.dist-info/WHEEL
sample_generated_20250730_01_repo-0.0.0.dist-info/top_level.txt
sample_generated_20250730_01_repo-0.0.0.dist-info/RECORD
