Metadata-Version: 2.4
Name: sample_generated_20250730_01_repo
Version: 0.0.0
Summary: My package description
Author-email: Mengni Zhang <monicamengni@gmail.com>
License: MIT
Keywords: one,two
Classifier: Programming Language :: Python :: 3
Classifier: Programming Language :: Python :: 3.10
Classifier: Programming Language :: Python :: 3.11
Classifier: Programming Language :: Python :: 3.12
Classifier: Programming Language :: Python :: 3.13
Requires-Python: >=3.10
Requires-Dist: numpy
Requires-Dist: importlib-metadata; python_version < "3.12"
Provides-Extra: test
Requires-Dist: pytest; extra == "test"
Requires-Dist: pytest-cov; extra == "test"
Provides-Extra: release
Requires-Dist: build; extra == "release"
Requires-Dist: twine; extra == "release"
Provides-Extra: static-code-qa
Requires-Dist: pre-commit; extra == "static-code-qa"
Provides-Extra: dev
Requires-Dist: sample_generated_20250730_01_repo[release,static-code-qa,test]; extra == "dev"
